Metadata-Version: 2.1
Name: pyTextColor
Version: 1.0.1
Summary: Simple Python Library to display text with color in Python Terminal!
Home-page: https://github.com/Sid72020123/pyTextColor/
Author: Siddhesh Chavan
Author-email: siddheshchavan2020@gmail.com
License: MIT
Keywords: color-outputs color text styling
Platform: UNKNOWN
Classifier: Development Status :: 5 - Production/Stable
Classifier: Intended Audience :: Education
Classifier: Operating System :: OS Independent
Classifier: License :: OSI Approved :: MIT License
Classifier: Programming Language :: Python :: 3
